e2b_desktop/__init__.py
e2b_desktop/main.py
e2b_desktop-2.1.0.dist-info/LICENSE
e2b_desktop-2.1.0.dist-info/METADATA
e2b_desktop-2.1.0.dist-info/WHEEL
e2b_desktop-2.1.0.dist-info/RECORD
