Metadata-Version: 2.1
Name: e2b-desktop
Version: 2.1.0
Summary: E2B Desktop Sandbox - Deskstop sandbox in cloud powered by E2B
Home-page: https://e2b.dev/
License: MIT
Author: e2b
Author-email: hello@e2b.dev
Requires-Python: >=3.9,<4.0
Classifier: License :: OSI Approved :: MIT License
Classifier: Programming Language :: Python :: 3
Classifier: Programming Language :: Python :: 3.9
Classifier: Programming Language :: Python :: 3.10
Classifier: Programming Language :: Python :: 3.11
Requires-Dist: e2b (>=2.3.0,<3.0.0)
Requires-Dist: pillow (>=11.1.0,<12.0.0)
Requires-Dist: requests (>=2.32.3,<3.0.0)
Project-URL: Bug Tracker, https://github.com/e2b-dev/desktop/issues
Project-URL: Repository, https://github.com/e2b-dev/desktop/tree/main/packages/python-sdk
